nondjango/__init__.py
nondjango/storages/__init__.py
nondjango/storages/files.py
nondjango/storages/storages.py
nondjango/storages/utils.py
nondjango_storages-0.3.4.dist-info/LICENSE
nondjango_storages-0.3.4.dist-info/LICENSE-DJANGO
nondjango_storages-0.3.4.dist-info/WHEEL
nondjango_storages-0.3.4.dist-info/METADATA
nondjango_storages-0.3.4.dist-info/RECORD
