Metadata-Version: 2.1
Name: nondjango-storages
Version: 0.3.4
Summary: nondjango-storages - Because the API is great but dependency on Django is not.
Home-page: https://github.com/alanjds/nondjango-storages/
License: UNKNOWN
Author: Alan Justino da Silva
Author-email: alan.justino@yahoo.com.br
Requires-Python: >=3.5
Classifier: Development Status :: 5 - Production/Stable
Classifier: Intended Audience :: Developers
Classifier: License :: OSI Approved :: Apache Software License
Classifier: Natural Language :: English
Classifier: Programming Language :: Python :: 3
Classifier: Programming Language :: Python :: 3.6
Requires-Dist: boto3
Requires-Dist: pytest ; extra == "test"
Requires-Dist: pytest-cov ; extra == "test"
Provides-Extra: test
